selene_hugr_qis_compiler-0.2.10.dist-info/RECORD
selene_hugr_qis_compiler-0.2.10.dist-info/WHEEL
selene_hugr_qis_compiler-0.2.10.dist-info/METADATA
selene_hugr_qis_compiler/selene_hugr_qis_compiler.abi3.so
selene_hugr_qis_compiler/__init__.py
selene_hugr_qis_compiler/py.typed
selene_hugr_qis_compiler/selene_hugr_qis_compiler.pyi
selene_hugr_qis_compiler/.dylibs/libc++abi.1.0.dylib
selene_hugr_qis_compiler/.dylibs/libunwind.1.0.dylib
selene_hugr_qis_compiler/.dylibs/libc++.1.0.dylib
