Metadata-Version: 2.4
Name: selene-hugr-qis-compiler
Version: 0.2.10
Classifier: Development Status :: 4 - Beta
Classifier: Intended Audience :: Developers
Classifier: Intended Audience :: Science/Research
Classifier: Topic :: Scientific/Engineering :: Quantum Computing
Classifier: Topic :: Software Development :: Compilers
Classifier: License :: OSI Approved :: Apache Software License
Classifier: Programming Language :: Rust
Classifier: Programming Language :: Python :: Implementation :: CPython
Classifier: Programming Language :: Python :: Implementation :: PyPy
Summary: A Python frontend for compiling HUGR to Quantinuum's QIS.
Author-email: Seyon Sivarajah <seyon.sivarajah@quantinuum.com>, TKET development team <tket-support@quantinuum.com>
Maintainer-email: Seyon Sivarajah <seyon.sivarajah@quantinuum.com>, TKET development team <tket-support@quantinuum.com>
Requires-Python: >=3.10
Project-URL: repository, https://github.com/CQCL/tket2/tree/main/qis-compiler
